morss/__init__.py
morss/__main__.py
morss/caching.py
morss/cli.py
morss/crawler.py
morss/feedify.ini
morss/feeds.py
morss/morss.py
morss/readabilite.py
morss/util.py
morss/wsgi.py
morss-20230627.2039.data/data/share/morss/LICENSE
morss-20230627.2039.data/data/share/morss/README.md
morss-20230627.2039.data/data/share/morss/www/index.html
morss-20230627.2039.data/data/share/morss/www/logo.svg
morss-20230627.2039.data/data/share/morss/www/sheet.xsl
morss-20230627.2039.data/scripts/morss-helper
morss-20230627.2039.dist-info/LICENSE
morss-20230627.2039.dist-info/METADATA
morss-20230627.2039.dist-info/WHEEL
morss-20230627.2039.dist-info/entry_points.txt
morss-20230627.2039.dist-info/top_level.txt
morss-20230627.2039.dist-info/RECORD
