Metadata-Version: 2.1
Name: morss
Version: 20230627.2039
Summary: Get full-text RSS feeds
Home-page: http://morss.it/
Author: pictuga
Author-email: contact@pictuga.com
License: AGPL v3
Project-URL: Source, https://git.pictuga.com/pictuga/morss
Project-URL: Bug Tracker, https://github.com/pictuga/morss/issues
Requires-Python: >=2.7
License-File: LICENSE
Requires-Dist: lxml
Requires-Dist: bs4
Requires-Dist: python-dateutil
Requires-Dist: chardet
Provides-Extra: dev
Requires-Dist: pylint ; extra == 'dev'
Requires-Dist: pyenchant ; extra == 'dev'
Requires-Dist: pytest ; extra == 'dev'
Requires-Dist: pytest-cov ; extra == 'dev'
Provides-Extra: full
Requires-Dist: redis ; extra == 'full'
Requires-Dist: diskcache ; extra == 'full'
Requires-Dist: gunicorn ; extra == 'full'
Requires-Dist: setproctitle ; extra == 'full'
